README.txt
setup.py
DownloadTool/__init__.py
DownloadTool/download.py
DownloadTool/st_log.py
DownloadTool.egg-info/PKG-INFO
DownloadTool.egg-info/SOURCES.txt
DownloadTool.egg-info/dependency_links.txt
DownloadTool.egg-info/requires.txt
DownloadTool.egg-info/top_level.txt
DownloadTool.egg-info/zip-safe
tests/DownloadTool_tests.py
tests/__init__.py