Metadata-Version: 1.1
Name: DownloadTool
Version: 0.0.1.3
Summary: A tool to download samples
Home-page: http://client.baidu.com
Author: caimaoy
Author-email: chenyue03@baidu.com
License: MIT
Keywords: caimaoy python download sample
Platform: UNKNOWN
Classifier: License :: OSI Approved :: MIT License
Classifier: Programming Language :: Python
Classifier: Intended Audience :: Developers
Classifier: Operating System :: Microsoft
